setup.cfg
setup.py
topic999/__init__.py
topic999/__main__.py
topic999/basemodel.py
topic999/emailextraction.py
topic999/lda.py
topic999/plotter.py
topic999/stats.py
topic999/test.py
topic999/utils.py
topic999.egg-info/PKG-INFO
topic999.egg-info/SOURCES.txt
topic999.egg-info/dependency_links.txt
topic999.egg-info/entry_points.txt
topic999.egg-info/requires.txt
topic999.egg-info/top_level.txt
topic999/coherence/__init__.py
topic999/coherence/semantic.py
topic999/dictionarylearning/__init__.py
topic999/dictionarylearning/bcd.py
topic999/dictionarylearning/sparse_coding.py
topic999/dictionarylearning/sparse_dictionary.py
topic999/preprocessing/__init__.py
topic999/preprocessing/emailsprocess.py
topic999/preprocessing/params.py
topic999/preprocessing/textcleaning.py
topic999/thresholdedsvd/__init__.py
topic999/thresholdedsvd/hyperparams.py
topic999/thresholdedsvd/tsvd.py
topic999/usereval/__init__.py
topic999/usereval/senddata.py
topic999/usereval/topicevalGUI.py
topic999/usereval/topiceval_application.py