Metadata-Version: 1.1
Name: topic999
Version: 1.0.1.dev1
Summary: Topic Model User Evaluation
Home-page: UNKNOWN
Author: topic999
Author-email: topic999@gmail.com
License: MIT
Keywords: topic models,evaluation,svd,sparse nmf,lda
Platform: UNKNOWN
Classifier: Development Status :: 1 - Planning
Classifier: Intended Audience :: Science/Research
Classifier: Topic :: Scientific/Engineering :: Information Analysis
Classifier: License :: OSI Approved :: MIT License
Classifier: Programming Language :: Python :: 2.7
Classifier: Programming Language :: Python :: 3.4
Classifier: Programming Language :: Python :: 3.5
